timed_functions/__init__.py
timed_functions/timed_functions.py
timed_functions-1.0.0.dist-info/LICENSE
timed_functions-1.0.0.dist-info/METADATA
timed_functions-1.0.0.dist-info/WHEEL
timed_functions-1.0.0.dist-info/top_level.txt
timed_functions-1.0.0.dist-info/RECORD
