Metadata-Version: 2.1
Name: timed-functions
Version: 1.0.0
Summary: Decorator to print how long each decorated function takes to complete.
Home-page: https://github.com/carloshenrique153/timed-functions
License: UNKNOWN
Platform: UNKNOWN
Classifier: Programming Language :: Python :: 3
Requires-Python: >=3.0
